lautpy/__init__.py
lautpy/pipe.py
lautpy-0.0.2.3.dist-info/licenses/LICENSE.txt
lautpy-0.0.2.3.dist-info/METADATA
lautpy-0.0.2.3.dist-info/WHEEL
lautpy-0.0.2.3.dist-info/top_level.txt
lautpy-0.0.2.3.dist-info/RECORD
