Metadata-Version: 2.4
Name: lautpy
Version: 0.0.2.3
Summary: A python utils package
Author-email: elimes <elimes@qq.com>
License: Apache-2.0
Project-URL: Homepage, https://github.com/elimes/lautpy
Project-URL: Repository, https://github.com/elimes/lautpy
Classifier: License :: OSI Approved :: Apache Software License
Classifier: Programming Language :: Python :: 3
Classifier: Programming Language :: Python :: 3.7
Classifier: Programming Language :: Python :: 3.8
Classifier: Programming Language :: Python :: 3.9
Classifier: Programming Language :: Python :: 3.10
Classifier: Programming Language :: Python :: 3.11
Classifier: Programming Language :: Python :: 3.12
Classifier: Operating System :: OS Independent
Requires-Python: >=3.7
License-File: LICENSE.txt
Requires-Dist: requests
Requires-Dist: numpy
Dynamic: license-file
